code_packager/__init__.py
code_packager/__main__.py
code_packager/actions.py
code_packager/cli.py
code_packager/comment_processor.py
code_packager/config.py
code_packager/exclude_patterns.conf
code_packager/file_filter.py
code_packager/main.py
code_packager/packager.py
code_packager/tui.py
code_packager/utils.py
code_packager/presets/basic.conf
code_packager/presets/complete.conf
code_packager/presets/git-friendly.conf
code_packager/presets/lightweight.conf
pack_my_code-0.3.4.dist-info/METADATA
pack_my_code-0.3.4.dist-info/WHEEL
pack_my_code-0.3.4.dist-info/entry_points.txt
pack_my_code-0.3.4.dist-info/licenses/LICENSE
pack_my_code-0.3.4.dist-info/RECORD
