Metadata-Version: 2.4
Name: pack-my-code
Version: 0.3.4
Summary: Easily zip your codebase while excluding unnecessary files like a pro! Say goodbye to bloated archives and hello to clean, lightweight packages. 🎉
Author-email: DealiAxy <dealiaxy@gmail.com>
License: MIT
License-File: LICENSE
Requires-Python: >=3.12
Requires-Dist: loguru>=0.7.3
Requires-Dist: pathspec>=0.12.1
Requires-Dist: textual>=0.70.0
